[
  {
    "rank": "1",
    "keyword": "意大利紧急求助中国",
    "href": "http://www.baidu.com/baidu?cl=3&tn=SE_baiduhomet8_jmjb7mjw&rsv_dl=fyb_top&fr=top1000&wd=%D2%E2%B4%F3%C0%FB%BD%F4%BC%B1%C7%F3%D6%FA%D6%D0%B9%FA"
  },
  {
    "rank": "2",
    "keyword": "罗志祥方回应分手",
    "href": "http://www.baidu.com/baidu?cl=3&tn=SE_baiduhomet8_jmjb7mjw&rsv_dl=fyb_top&fr=top1000&wd=%C2%DE%D6%BE%CF%E9%B7%BD%BB%D8%D3%A6%B7%D6%CA%D6"
  },
  {
    "rank": "3",
    "keyword": "捐款13万退回12万",
    "href": "http://www.baidu.com/baidu?cl=3&tn=SE_baiduhomet8_jmjb7mjw&rsv_dl=fyb_top&fr=top1000&wd=%BE%E8%BF%EE13%CD%F2%CD%CB%BB%D812%CD%F2"
  },
  {
    "rank": "4",
    "keyword": "花木兰首映获好评",
    "href": "http://www.baidu.com/baidu?cl=3&tn=SE_baiduhomet8_jmjb7mjw&rsv_dl=fyb_top&fr=top1000&wd=%BB%A8%C4%BE%C0%BC%CA%D7%D3%B3%BB%F1%BA%C3%C6%C0"
  },
  {
    "rank": "5",
    "keyword": "中国专家赴意大利",
    "href": "http://www.baidu.com/baidu?cl=3&tn=SE_baiduhomet8_jmjb7mjw&rsv_dl=fyb_top&fr=top1000&wd=%D6%D0%B9%FA%D7%A8%BC%D2%B8%B0%D2%E2%B4%F3%C0%FB"
  },
  {
    "rank": "6",
    "keyword": "淘宝回应崩了",
    "href": "http://www.baidu.com/baidu?cl=3&tn=SE_baiduhomet8_jmjb7mjw&rsv_dl=fyb_top&fr=top1000&wd=%CC%D4%B1%A6%BB%D8%D3%A6%B1%C0%C1%CB"
  },
  {
    "rank": "7",
    "keyword": "工信部约谈特斯拉",
    "href": "http://www.baidu.com/baidu?cl=3&tn=SE_baiduhomet8_jmjb7mjw&rsv_dl=fyb_top&fr=top1000&wd=%B9%A4%D0%C5%B2%BF%D4%BC%CC%B8%CC%D8%CB%B9%C0%AD"
  },
  {
    "rank": "8",
    "keyword": "滴血15分钟出结果",
    "href": "http://www.baidu.com/baidu?cl=3&tn=SE_baiduhomet8_jmjb7mjw&rsv_dl=fyb_top&fr=top1000&wd=%B5%CE%D1%AA15%B7%D6%D6%D3%B3%F6%BD%E1%B9%FB"
  },
  {
    "rank": "9",
    "keyword": "特斯拉生产总监离职",
    "href": "http://www.baidu.com/baidu?cl=3&tn=SE_baiduhomet8_jmjb7mjw&rsv_dl=fyb_top&fr=top1000&wd=%CC%D8%CB%B9%C0%AD%C9%FA%B2%FA%D7%DC%BC%E0%C0%EB%D6%B0"
  },
  {
    "rank": "10",
    "keyword": "潜江取消26号通告",
    "href": "http://www.baidu.com/baidu?cl=3&tn=SE_baiduhomet8_jmjb7mjw&rsv_dl=fyb_top&fr=top1000&wd=%C7%B1%BD%AD%C8%A1%CF%FB26%BA%C5%CD%A8%B8%E6"
  },
  {
    "rank": "11",
    "keyword": "伊朗建方舱医院",
    "href": "http://www.baidu.com/baidu?cl=3&tn=SE_baiduhomet8_jmjb7mjw&rsv_dl=fyb_top&fr=top1000&wd=%D2%C1%C0%CA%BD%A8%B7%BD%B2%D5%D2%BD%D4%BA"
  },
  {
    "rank": "12",
    "keyword": "吴尊道歉",
    "href": "http://www.baidu.com/baidu?cl=3&tn=SE_baiduhomet8_jmjb7mjw&rsv_dl=fyb_top&fr=top1000&wd=%CE%E2%D7%F0%B5%C0%C7%B8"
  },
  {
    "rank": "13",
    "keyword": "塔利班发动32次袭击",
    "href": "http://www.baidu.com/baidu?cl=3&tn=SE_baiduhomet8_jmjb7mjw&rsv_dl=fyb_top&fr=top1000&wd=%CB%FE%C0%FB%B0%E0%B7%A2%B6%AF32%B4%CE%CF%AE%BB%F7"
  },
  {
    "rank": "14",
    "keyword": "意大利监狱暴动",
    "href": "http://www.baidu.com/baidu?cl=3&tn=SE_baiduhomet8_jmjb7mjw&rsv_dl=fyb_top&fr=top1000&wd=%D2%E2%B4%F3%C0%FB%BC%E0%D3%FC%B1%A9%B6%AF"
  },
  {
    "rank": "15",
    "keyword": "湖北继续延迟开学",
    "href": "http://www.baidu.com/baidu?cl=3&tn=SE_baiduhomet8_jmjb7mjw&rsv_dl=fyb_top&fr=top1000&wd=%BA%FE%B1%B1%BC%CC%D0%F8%D1%D3%B3%D9%BF%AA%D1%A7"
  },
  {
    "rank": "16",
    "keyword": "微软 首席科学官",
    "href": "http://www.baidu.com/baidu?cl=3&tn=SE_baiduhomet8_jmjb7mjw&rsv_dl=fyb_top&fr=top1000&wd=%CE%A2%C8%ED%20%CA%D7%CF%AF%BF%C6%D1%A7%B9%D9"
  },
  {
    "rank": "17",
    "keyword": "意大利封闭全国",
    "href": "http://www.baidu.com/baidu?cl=3&tn=SE_baiduhomet8_jmjb7mjw&rsv_dl=fyb_top&fr=top1000&wd=%D2%E2%B4%F3%C0%FB%B7%E2%B1%D5%C8%AB%B9%FA"
  },
  {
    "rank": "18",
    "keyword": "朱和平医生去世",
    "href": "http://www.baidu.com/baidu?cl=3&tn=SE_baiduhomet8_jmjb7mjw&rsv_dl=fyb_top&fr=top1000&wd=%D6%EC%BA%CD%C6%BD%D2%BD%C9%FA%C8%A5%CA%C0"
  },
  {
    "rank": "19",
    "keyword": "韩国累计7513例",
    "href": "http://www.baidu.com/baidu?cl=3&tn=SE_baiduhomet8_jmjb7mjw&rsv_dl=fyb_top&fr=top1000&wd=%BA%AB%B9%FA%C0%DB%BC%C67513%C0%FD"
  },
  {
    "rank": "20",
    "keyword": "19年国内旅游人数",
    "href": "http://www.baidu.com/baidu?cl=3&tn=SE_baiduhomet8_jmjb7mjw&rsv_dl=fyb_top&fr=top1000&wd=19%C4%EA%B9%FA%C4%DA%C2%C3%D3%CE%C8%CB%CA%FD"
  },
  {
    "rank": "21",
    "keyword": "微信回应被下架",
    "href": "http://www.baidu.com/baidu?cl=3&tn=SE_baiduhomet8_jmjb7mjw&rsv_dl=fyb_top&fr=top1000&wd=%CE%A2%D0%C5%BB%D8%D3%A6%B1%BB%CF%C2%BC%DC"
  },
  {
    "rank": "22",
    "keyword": "意大利病死率最高",
    "href": "http://www.baidu.com/baidu?cl=3&tn=SE_baiduhomet8_jmjb7mjw&rsv_dl=fyb_top&fr=top1000&wd=%D2%E2%B4%F3%C0%FB%B2%A1%CB%C0%C2%CA%D7%EE%B8%DF"
  },
  {
    "rank": "23",
    "keyword": "詹姆斯倒地抢断",
    "href": "http://www.baidu.com/baidu?cl=3&tn=SE_baiduhomet8_jmjb7mjw&rsv_dl=fyb_top&fr=top1000&wd=%D5%B2%C4%B7%CB%B9%B5%B9%B5%D8%C7%C0%B6%CF"
  },
  {
    "rank": "24",
    "keyword": "美延长华为许可证",
    "href": "http://www.baidu.com/baidu?cl=3&tn=SE_baiduhomet8_jmjb7mjw&rsv_dl=fyb_top&fr=top1000&wd=%C3%C0%D1%D3%B3%A4%BB%AA%CE%AA%D0%ED%BF%C9%D6%A4"
  },
  {
    "rank": "25",
    "keyword": "刘真老公再发文",
    "href": "http://www.baidu.com/baidu?cl=3&tn=SE_baiduhomet8_jmjb7mjw&rsv_dl=fyb_top&fr=top1000&wd=%C1%F5%D5%E6%C0%CF%B9%AB%D4%D9%B7%A2%CE%C4"
  },
  {
    "rank": "26",
    "keyword": "民众支持法国封城",
    "href": "http://www.baidu.com/baidu?cl=3&tn=SE_baiduhomet8_jmjb7mjw&rsv_dl=fyb_top&fr=top1000&wd=%C3%F1%D6%DA%D6%A7%B3%D6%B7%A8%B9%FA%B7%E2%B3%C7"
  },
  {
    "rank": "27",
    "keyword": "美国从阿富汗撤军",
    "href": "http://www.baidu.com/baidu?cl=3&tn=SE_baiduhomet8_jmjb7mjw&rsv_dl=fyb_top&fr=top1000&wd=%C3%C0%B9%FA%B4%D3%B0%A2%B8%BB%BA%B9%B3%B7%BE%FC"
  },
  {
    "rank": "28",
    "keyword": "马萨诸塞紧急状态",
    "href": "http://www.baidu.com/baidu?cl=3&tn=SE_baiduhomet8_jmjb7mjw&rsv_dl=fyb_top&fr=top1000&wd=%C2%ED%C8%F8%D6%EE%C8%FB%BD%F4%BC%B1%D7%B4%CC%AC"
  },
  {
    "rank": "29",
    "keyword": "泉州酒店遇难名单",
    "href": "http://www.baidu.com/baidu?cl=3&tn=SE_baiduhomet8_jmjb7mjw&rsv_dl=fyb_top&fr=top1000&wd=%C8%AA%D6%DD%BE%C6%B5%EA%D3%F6%C4%D1%C3%FB%B5%A5"
  },
  {
    "rank": "30",
    "keyword": "白宇被曝室内吸烟",
    "href": "http://www.baidu.com/baidu?cl=3&tn=SE_baiduhomet8_jmjb7mjw&rsv_dl=fyb_top&fr=top1000&wd=%B0%D7%D3%EE%B1%BB%C6%D8%CA%D2%C4%DA%CE%FC%D1%CC"
  },
  {
    "rank": "31",
    "keyword": "葡萄牙总统隔离",
    "href": "http://www.baidu.com/baidu?cl=3&tn=SE_baiduhomet8_jmjb7mjw&rsv_dl=fyb_top&fr=top1000&wd=%C6%CF%CC%D1%D1%C0%D7%DC%CD%B3%B8%F4%C0%EB"
  },
  {
    "rank": "32",
    "keyword": "德国拦截瑞士口罩",
    "href": "http://www.baidu.com/baidu?cl=3&tn=SE_baiduhomet8_jmjb7mjw&rsv_dl=fyb_top&fr=top1000&wd=%B5%C2%B9%FA%C0%B9%BD%D8%C8%F0%CA%BF%BF%DA%D5%D6"
  },
  {
    "rank": "33",
    "keyword": "日本议员拍卖口罩",
    "href": "http://www.baidu.com/baidu?cl=3&tn=SE_baiduhomet8_jmjb7mjw&rsv_dl=fyb_top&fr=top1000&wd=%C8%D5%B1%BE%D2%E9%D4%B1%C5%C4%C2%F4%BF%DA%D5%D6"
  },
  {
    "rank": "34",
    "keyword": "拳手向朴宰范道歉",
    "href": "http://www.baidu.com/baidu?cl=3&tn=SE_baiduhomet8_jmjb7mjw&rsv_dl=fyb_top&fr=top1000&wd=%C8%AD%CA%D6%CF%F2%C6%D3%D4%D7%B7%B6%B5%C0%C7%B8"
  },
  {
    "rank": "35",
    "keyword": "携程高管自愿降薪",
    "href": "http://www.baidu.com/baidu?cl=3&tn=SE_baiduhomet8_jmjb7mjw&rsv_dl=fyb_top&fr=top1000&wd=%D0%AF%B3%CC%B8%DF%B9%DC%D7%D4%D4%B8%BD%B5%D0%BD"
  },
  {
    "rank": "36",
    "keyword": "南非核电站故障",
    "href": "http://www.baidu.com/baidu?cl=3&tn=SE_baiduhomet8_jmjb7mjw&rsv_dl=fyb_top&fr=top1000&wd=%C4%CF%B7%C7%BA%CB%B5%E7%D5%BE%B9%CA%D5%CF"
  },
  {
    "rank": "37",
    "keyword": "勇士无缘季后赛",
    "href": "http://www.baidu.com/baidu?cl=3&tn=SE_baiduhomet8_jmjb7mjw&rsv_dl=fyb_top&fr=top1000&wd=%D3%C2%CA%BF%CE%DE%D4%B5%BC%BE%BA%F3%C8%FC"
  },
  {
    "rank": "38",
    "keyword": "疫情防控思政大课",
    "href": "http://www.baidu.com/baidu?cl=3&tn=SE_baiduhomet8_jmjb7mjw&rsv_dl=fyb_top&fr=top1000&wd=%D2%DF%C7%E9%B7%C0%BF%D8%CB%BC%D5%FE%B4%F3%BF%CE"
  },
  {
    "rank": "39",
    "keyword": "美国病例增至687",
    "href": "http://www.baidu.com/baidu?cl=3&tn=SE_baiduhomet8_jmjb7mjw&rsv_dl=fyb_top&fr=top1000&wd=%C3%C0%B9%FA%B2%A1%C0%FD%D4%F6%D6%C1687"
  },
  {
    "rank": "40",
    "keyword": "黄冈恢复正常医疗",
    "href": "http://www.baidu.com/baidu?cl=3&tn=SE_baiduhomet8_jmjb7mjw&rsv_dl=fyb_top&fr=top1000&wd=%BB%C6%B8%D4%BB%D6%B8%B4%D5%FD%B3%A3%D2%BD%C1%C6"
  },
  {
    "rank": "41",
    "keyword": "新型冠状病毒",
    "href": "http://www.baidu.com/baidu?cl=3&tn=SE_baiduhomet8_jmjb7mjw&rsv_dl=fyb_top&fr=top1000&wd=%D0%C2%D0%CD%B9%DA%D7%B4%B2%A1%B6%BE"
  },
  {
    "rank": "42",
    "keyword": "女童19楼坠落身亡",
    "href": "http://www.baidu.com/baidu?cl=3&tn=SE_baiduhomet8_jmjb7mjw&rsv_dl=fyb_top&fr=top1000&wd=%C5%AE%CD%AF19%C2%A5%D7%B9%C2%E4%C9%ED%CD%F6"
  },
  {
    "rank": "43",
    "keyword": "伊朗确诊突破8千",
    "href": "http://www.baidu.com/baidu?cl=3&tn=SE_baiduhomet8_jmjb7mjw&rsv_dl=fyb_top&fr=top1000&wd=%D2%C1%C0%CA%C8%B7%D5%EF%CD%BB%C6%C68%C7%A7"
  },
  {
    "rank": "44",
    "keyword": "北京供暖期延长",
    "href": "http://www.baidu.com/baidu?cl=3&tn=SE_baiduhomet8_jmjb7mjw&rsv_dl=fyb_top&fr=top1000&wd=%B1%B1%BE%A9%B9%A9%C5%AF%C6%DA%D1%D3%B3%A4"
  },
  {
    "rank": "45",
    "keyword": "美国8州紧急状态",
    "href": "http://www.baidu.com/baidu?cl=3&tn=SE_baiduhomet8_jmjb7mjw&rsv_dl=fyb_top&fr=top1000&wd=%C3%C0%B9%FA8%D6%DD%BD%F4%BC%B1%D7%B4%CC%AC"
  },
  {
    "rank": "46",
    "keyword": "苏丹总理躲过暗杀",
    "href": "http://www.baidu.com/baidu?cl=3&tn=SE_baiduhomet8_jmjb7mjw&rsv_dl=fyb_top&fr=top1000&wd=%CB%D5%B5%A4%D7%DC%C0%ED%B6%E3%B9%FD%B0%B5%C9%B1"
  },
  {
    "rank": "47",
    "keyword": "韩国新增242例",
    "href": "http://www.baidu.com/baidu?cl=3&tn=SE_baiduhomet8_jmjb7mjw&rsv_dl=fyb_top&fr=top1000&wd=%BA%AB%B9%FA%D0%C2%D4%F6242%C0%FD"
  },
  {
    "rank": "48",
    "keyword": "韩寒认养两头河马",
    "href": "http://www.baidu.com/baidu?cl=3&tn=SE_baiduhomet8_jmjb7mjw&rsv_dl=fyb_top&fr=top1000&wd=%BA%AB%BA%AE%C8%CF%D1%F8%C1%BD%CD%B7%BA%D3%C2%ED"
  },
  {
    "rank": "49",
    "keyword": "热刺0比3莱比锡",
    "href": "http://www.baidu.com/baidu?cl=3&tn=SE_baiduhomet8_jmjb7mjw&rsv_dl=fyb_top&fr=top1000&wd=%C8%C8%B4%CC0%B1%C83%C0%B3%B1%C8%CE%FD"
  },
  {
    "rank": "50",
    "keyword": "泉州酒店救出59人",
    "href": "http://www.baidu.com/baidu?cl=3&tn=SE_baiduhomet8_jmjb7mjw&rsv_dl=fyb_top&fr=top1000&wd=%C8%AA%D6%DD%BE%C6%B5%EA%BE%C8%B3%F659%C8%CB"
  }
]